{
    "allow_bike": false,
    "allow_escape_rope": false,
    "allow_running": true,
    "battle_scene": "MAP_BATTLE_SCENE_NORMAL",
    "bg_events": [
    ],
    "connections": null,
    "coord_events": [
    ],
    "id": "MAP_LITTLEROOT_TOWN_RIVAL_HOUSE_QUEST",
    "layout": "LAYOUT_LITTLEROOT_TOWN_RIVAL_HOUSE_QUEST",
    "map_type": "MAP_TYPE_INDOOR",
    "music": "MUS_DAN02",
    "name": "Littleroot_Town_Rival_HouseQuest",
    "object_events": [
        {
            "elevation": 3,
            "flag": "0",
            "graphics_id": "OBJ_EVENT_GFX_RIVAL_DAWN_NORMAL",
            "movement_range_x": 0,
            "movement_range_y": 0,
            "movement_type": "MOVEMENT_TYPE_NONE",
            "script": "NULL",
            "trainer_sight_or_berry_tree_id": "0",
            "trainer_type": "TRAINER_TYPE_NONE",
            "x": 13,
            "y": 10
        }
    ],
    "region_map_section": "MAPSEC_LITTLEROOT_TOWN",
    "requires_flash": false,
    "show_map_name": true,
    "warp_events": [
        {
            "dest_map": "MAP_LITTLEROOT_TOWN_DAWNS_HOUSE_1F",
            "dest_warp_id": 2,
            "elevation": 3,
            "x": 7,
            "y": 8
        }
    ],
    "weather": "WEATHER_NONE"
}
